pycounts_ic/__init__.py
pycounts_ic/plotting.py
pycounts_ic/pycounts_ic.py
pycounts_ic-0.1.1.dist-info/LICENSE
pycounts_ic-0.1.1.dist-info/METADATA
pycounts_ic-0.1.1.dist-info/WHEEL
pycounts_ic-0.1.1.dist-info/RECORD
