Metadata-Version: 2.1
Name: pycounts-ic
Version: 0.1.1
Summary: Calculate word counts in a text file.
License: MIT
Author: Ivo Camargo
Requires-Python: >=3.10
Classifier: License :: OSI Approved :: MIT License
Classifier: Programming Language :: Python :: 3
Classifier: Programming Language :: Python :: 3.10
Classifier: Programming Language :: Python :: 3.11
Requires-Dist: matplotlib (>=3.7.1,<4.0.0)
